{
  "id": "OP12-041",
  "set": "OP12",
  "number": 41,
  "name": "Sanji",
  "category": "Leader",
  "colors": [
    "Blue"
  ],
  "attribute": "Strike",
  "types": [
    "Straw Hat Crew",
    "The Vinsmoke Family"
  ],
  "rarity": "R",
  "art": "/cards/OP12/OP12-041.png",
  "stats": {
    "cost": null,
    "power": null,
    "life": 4,
    "counter": {
      "present": true,
      "value": 5000
    }
  },
  "keywords": [],
  "trigger": null,
  "text": "Activate: Main Once Per Turn DON!!-1: Activate up to 1 {Straw Hat Crew} type Event card from your hand with an original cost of 3 or less. When Attacking If the number of DON!! cards on your field is equal to or less than the number on your opponent's field, add up to 1 DON!! card from your DON!! deck and rest it.",
  "abilities": [
    {
      "timing": "Activate: Main",
      "frequency": "Once Per Turn",
      "donReq": 1,
      "cost": {
        "restDonFromCostArea": 0
      },
      "effect": {
        "text": "Activate up to 1 {Straw Hat Crew} type Event card from your hand with an original cost of 3 or less.",
        "powerMod": null,
        "giveDon": null
      }
    },
    {
      "timing": "When Attacking",
      "frequency": null,
      "donReq": null,
      "cost": {
        "restDonFromCostArea": 0
      },
      "effect": {
        "text": "If the number of DON!! cards on your field is equal to or less than the number on your opponent's field, add up to 1 DON!! card from your DON!! deck and rest it.",
        "powerMod": null,
        "giveDon": {
          "quantity": 1,
          "state": "rested",
          "from": "DON!! deck",
          "to": [
            "self"
          ]
        }
      }
    }
  ],
  "meta": {
    "notes": null
  }
}
