{
  "cardName": "Monkey.D.Garp",
  "cardId": "OP12-056",
  "cardType": "character",
  "colors": ["blue"],
  "cost": 8,
  "power": 8000,
  "counter": 1000,
  "attributes": ["strike"],
  "types": ["Navy"],
  "traits": ["navy"],
  "rarity": "SR",
  "setId": "OP12",
  "cardNumber": "056",
  "printedText": "[On Play] You may trash 1 card from your hand: Play up to 1 blue {Navy} Character card with a power of 8000 or less other than [Monkey.D.Garp] from your hand.",
  "keywords": [],
  "abilities": [
    {
      "timing": "onPlay",
      "cost": {
        "type": "trashFromHand",
        "minCards": 1,
        "maxCards": 1,
        "may": true
      },
      "selectors": {
        "garpPlayTarget": {
          "side": "self",
          "type": "character",
          "zones": ["hand"],
          "filters": [
            {
              "field": "colors",
              "op": "=",
              "value": "blue"
            },
            {
              "field": "traits",
              "op": "=",
              "value": "navy"
            },
            {
              "field": "power",
              "op": "<=",
              "value": 8000
            },
            {
              "field": "cardName",
              "op": "!=",
              "value": "Monkey.D.Garp"
            }
          ],
          "min": 0,
          "max": 1,
          "upTo": true,
          "whoChooses": "self"
        }
      },
      "actions": [
        {
          "type": "playCard",
          "sourceZone": "hand",
          "target": "garpPlayTarget",
          "payCost": false
        }
      ]
    }
  ]
}
