{
  "id": "OP07-021",
  "set": "OP07",
  "number": 21,
  "name": "Uroge",
  "category": "Character",
  "colors": [
    "Green"
  ],
  "attribute": "Strike",
  "types": [
    "Supernovas",
    "Fallen Monk Pirates"
  ],
  "rarity": "R",
  "art": "/cards/OP07/OP07-021.png",
  "stats": {
    "cost": 4,
    "power": 5000,
    "life": null,
    "counter": {
      "present": true,
      "value": 1000
    }
  },
  "keywords": [
    "Blocker",
    "End of Your Turn"
  ],
  "trigger": null,
  "text": "Blocker (After your opponent declares an attack, you may rest this card to make it the new target of the attack.)\nEnd of Your Turn: Set up to one of your Don!! cards as active.",
  "abilities": [
    {
      "timing": "Blocker",
      "frequency": null,
      "donReq": null,
      "cost": {
        "restDonFromCostArea": 0
      },
      "effect": {
        "text": "After your opponent declares an attack, you may rest this card to make it the new target of the attack.",
        "powerMod": null,
        "giveDon": null
      }
    },
    {
      "timing": "End of Your Turn",
      "frequency": null,
      "donReq": null,
      "cost": {
        "restDonFromCostArea": 0
      },
      "effect": {
        "text": "Set up to one of your Don!! cards as active.",
        "powerMod": null,
        "giveDon": null
      }
    }
  ],
  "meta": {
    "notes": null
  }
}
