{
  "cardName": "Yamato",
  "cardId": "ST13-016",
  "cardType": "character",
  "colors": ["yellow"],
  "cost": 5,
  "power": 4000,
  "counter": 2000,
  "attributes": ["strike"],
  "types": ["Wano Country"],
  "traits": ["wanoCountry"],
  "rarity": "C",
  "setId": "ST13",
  "cardNumber": "016",
  "printedText": "Rush (This card can attack on the turn in which it is played.) [On Play] Look at all your life cards, place 1 of the cards on the top of your deck. Then, return your life cards in your desired order.",
  "keywords": ["Rush"],
  "abilities": [
    {
      "timing": "onPlay",
      "selectors": {
        "lifeChoice": {
          "side": "self",
          "type": "any",
          "zones": ["life"],
          "min": 1,
          "max": 1,
          "whoChooses": "self"
        }
      },
      "actions": [
        {
          "type": "revealLife",
          "count": 1,
          "side": "self",
          "all": true,
          "ordering": "keep"
        },
        {
          "type": "moveCard",
          "target": "lifeChoice",
          "destination": "topOfDeck",
          "ordering": "keep"
        },
        {
          "type": "revealLife",
          "count": 1,
          "side": "self",
          "all": true,
          "ordering": "chosen"
        }
      ]
    }
  ]
}
