{
  "id": "OP02-048",
  "set": "OP02",
  "number": 48,
  "name": "Flower Capital",
  "category": "Stage",
  "colors": ["Blue"],
  "attribute": null,
  "types": ["Wano Country"],
  "rarity": "C",
  "art": "/cards/OP02/OP02-048.png",
  "stats": {
    "cost": 1,
    "power": null,
    "life": null,
    "counter": { "present": false, "value": 0 }
  },
  "keywords": ["Activate: Main"],
  "trigger": null,
  "text": "Activate: Main: You may trash 1 [Wano Country] type card and rest this card: Set up to 1 of your DON!! cards as active.",
  "abilities": [
    {
      "timing": "Activate: Main",
      "frequency": null,
      "donReq": null,
      "cost": { "restDonFromCostArea": 0 },
      "effect": {
        "text": "You may trash 1 [Wano Country] type card and rest this card: Set up to 1 of your DON!! cards as active.",
        "grants": ["active"],
        "powerMod": null,
        "targets": ["Don!!"],
        "conditions": ["Trash 1 Wano Country type card", "Rest this card"]
      }
    }
  ],
  "meta": { "notes": null }
}