{
  "id": "OP11-083",
  "set": "OP11",
  "number": 83,
  "name": "Caribou",
  "category": "Character",
  "colors": [
    "Black"
  ],
  "attribute": null,
  "types": [
    "Caribou Pirates"
  ],
  "rarity": "SP",
  "art": "/cards/OP11/OP11-083.png",
  "stats": {
    "cost": 1,
    "power": 2000,
    "life": null,
    "counter": {
      "present": true,
      "value": 2000
    }
  },
  "keywords": [
    "Blocker",
    "On Play"
  ],
  "trigger": null,
  "text": "Blocker (After your opponent declares an attack, you may rest this card to make it the new target of the attack.)\nOn Play Trash 2 cards from your hand.",
  "abilities": [
    {
      "timing": "On Play",
      "frequency": null,
      "donReq": null,
      "cost": {
        "restDonFromCostArea": 0
      },
      "effect": {
        "text": "Trash 2 cards from your hand.",
        "powerMod": null,
        "giveDon": null
      }
    },
    {
      "timing": "Blocker",
      "frequency": null,
      "donReq": null,
      "cost": {
        "restDonFromCostArea": 0
      },
      "effect": {
        "text": "After your opponent declares an attack, you may rest this card to make it the new target of the attack.",
        "powerMod": null,
        "giveDon": null
      }
    }
  ],
  "meta": {
    "notes": null
  }
}
