{
  "cardName": "Chonmage",
  "cardId": "OP11-107",
  "cardType": "character",
  "colors": ["yellow"],
  "cost": 5,
  "power": 6000,
  "counter": 1000,
  "attributes": ["strike"],
  "types": ["Sea Kings"],
  "traits": ["seaKings"],
  "rarity": "C",
  "setId": "OP11",
  "cardNumber": "107",
  "printedText": "[Blocker]\n[Activate: Main] [Once Per Turn] If your Leader is [Shirahoshi], you may turn 1 card from the top of your Life cards face-down: At the end of your turn, set this Character as active.",
  "keywords": ["Blocker"],
  "abilities": [
    {
      "timing": "activateMain",
      "frequency": "oncePerTurn",
      "condition": {
        "field": "leaderIs_shirahoshi",
        "op": "=",
        "value": true
      },
      "cost": {
        "type": "setTopLifeFace",
        "side": "self",
        "count": 1,
        "faceUp": false,
        "may": true
      },
      "actions": [
        {
          "type": "replacementEffect",
          "duration": "thisTurn",
          "event": "endOfYourTurn",
          "target": {
            "side": "self",
            "type": "thisCard"
          },
          "actions": [
            {
              "type": "setState",
              "state": "active",
              "target": {
                "side": "self",
                "type": "thisCard"
              }
            }
          ]
        }
      ]
    }
  ]
}
