{
  "id": "OP11-091",
  "set": "OP11",
  "number": 91,
  "name": "Berry Good",
  "category": "Character",
  "colors": [
    "Black"
  ],
  "attribute": null,
  "types": [
    "Navy"
  ],
  "rarity": "UC",
  "art": "/cards/OP11/OP11-091.png",
  "stats": {
    "cost": 4,
    "power": null,
    "life": null,
    "counter": {
      "present": true,
      "value": 2000
    }
  },
  "keywords": [
    "On Play"
  ],
  "trigger": null,
  "text": "On Play: Your opponent places 3 Event cards from their trash to the bottom of their deck in any order.",
  "abilities": [
    {
      "timing": "On Play",
      "frequency": null,
      "donReq": null,
      "cost": {
        "restDonFromCostArea": 0
      },
      "effect": {
        "text": "Your opponent places 3 Event cards from their trash to the bottom of their deck in any order.",
        "powerMod": null,
        "giveDon": null
      }
    }
  ],
  "meta": {
    "notes": null
  }
}
