{
  "cardName": "Koala",
  "cardId": "OP05-006",
  "cardType": "character",
  "colors": [
    "red"
  ],
  "cost": 2,
  "power": 3000,
  "counter": 2000,
  "types": [
    "Revolutionary Army"
  ],
  "rarity": "SR",
  "setId": "OP05",
  "cardNumber": "006",
  "printedText": "[On Play] If your Leader has the type {Revolutionary Army}, give up to 1 of your opponent's Characters -3000 Power during this turn.",
  "keywords": [],
  "abilities": [
    {
      "timing": "onPlay",
      "frequency": "none",
      "condition": {
        "field": "leaderHasType",
        "op": "=",
        "value": "Revolutionary Army"
      },
      "selectors": {
        "debuffTarget": {
          "side": "opponent",
          "type": "character",
          "zones": [
            "character"
          ],
          "min": 0,
          "max": 1,
          "upTo": true,
          "whoChooses": "self",
          "bindAs": "debuffTarget"
        }
      },
      "actions": [
        {
          "type": "modifyStat",
          "stat": "power",
          "mode": "add",
          "amount": -3000,
          "duration": "thisTurn",
          "target": "debuffTarget"
        }
      ]
    }
  ],
  "attributes": [
    "strike"
  ],
  "traits": [
    "revolutionaryArmy"
  ]
}
