{
  "id": "ST04-003",
  "set": "ST04",
  "number": 3,
  "name": "Kaido",
  "category": "Character",
  "colors": ["Purple"],
  "attribute": "Strike",
  "types": ["The Four Emperors", "Animal Kingdom Pirates"],
  "rarity": null,
  "art": "/cards/ST04/ST04-003.png",
  "stats": { "cost": 9, "power": 10000, "life": null, "counter": { "present": false, "value": 0 } },
  "keywords": ["On Play", "DON!! -5", "Rush"],
  "trigger": null,
  "text": "On Play — DON!! -5: K.O. 1 of your opponent's Characters with a cost of 6 or less. This Character gains Rush during this turn.",
  "abilities": [
    {"timing": "On Play", "frequency": null, "donReq": 5, "cost": {"restDonFromCostArea": 0}, "effect": {"text": "K.O. 1 opponent Character with cost 6 or less; this gains Rush this turn.", "grants": ["Rush"], "powerMod": null, "targets": ["oneOpponentCharacter"], "conditions": ["donAttached"]}}
  ],
  "meta": {"notes": null}
}
