{
  "cardName": "Perona",
  "cardId": "OP14-111",
  "cardType": "character",
  "colors": ["yellow"],
  "cost": 4,
  "power": 5000,
  "counter": 1000,
  "attributes": ["special"],
  "types": [
    "Thriller Bark Pirates"
  ],
  "traits": [
    "thrillerBarkPirates"
  ],
  "rarity": "R",
  "setId": "OP14",
  "cardNumber": "111",
  "printedText": "[On Play] / [On K.O.] Up to 1 of your opponent's Characters with a cost of 6 or less cannot attack until the end of your opponent's next turn.\n[Trigger] Play up to 1 {Thriller Bark Pirates} type Character card with a cost of 4 or less from your trash rested.",
  "keywords": [],
  "abilities": [
    {
      "timing": "onPlay",
      "selectors": {
        "opponentCharCost6OrLess": {
          "side": "opponent",
          "type": "character",
          "zones": ["character"],
          "filters": [
            {
              "field": "cost",
              "op": "<=",
              "value": 6
            }
          ],
          "min": 0,
          "max": 1,
          "upTo": true,
          "whoChooses": "self"
        }
      },
      "actions": [
        {
          "type": "restrict",
          "restrictionKind": "attack",
          "target": "opponentCharCost6OrLess",
          "duration": "untilEndOfOpponentsNextTurn"
        }
      ]
    },
    {
      "timing": "onKO",
      "selectors": {
        "opponentCharCost6OrLess": {
          "side": "opponent",
          "type": "character",
          "zones": ["character"],
          "filters": [
            {
              "field": "cost",
              "op": "<=",
              "value": 6
            }
          ],
          "min": 0,
          "max": 1,
          "upTo": true,
          "whoChooses": "self"
        }
      },
      "actions": [
        {
          "type": "restrict",
          "restrictionKind": "attack",
          "target": "opponentCharCost6OrLess",
          "duration": "untilEndOfOpponentsNextTurn"
        }
      ]
    },
    {
      "timing": "trigger",
      "selectors": {
        "trashTbpCharCost4OrLess": {
          "side": "self",
          "type": "character",
          "zones": ["trash"],
          "filters": [
            {
              "field": "traits",
              "op": "=",
              "value": "thrillerBarkPirates"
            },
            {
              "field": "cost",
              "op": "<=",
              "value": 4
            }
          ],
          "min": 0,
          "max": 1,
          "upTo": true,
          "whoChooses": "self"
        }
      },
      "actions": [
        {
          "type": "playCard",
          "sourceZone": "trash",
          "target": "trashTbpCharCost4OrLess",
          "enterRested": true,
          "payCost": false
        }
      ]
    }
  ]
}
