{
  "cardName": "Donquixote Rosinante",
  "cardId": "OP10-072",
  "cardType": "character",
  "colors": ["purple"],
  "cost": 5,
  "power": 6000,
  "counter": 1000,
  "attributes": ["special"],
  "types": ["Navy", "Donquixote Pirates"],
  "traits": ["navy", "donquixotePirates"],
  "rarity": "SR",
  "setId": "OP10",
  "cardNumber": "072",
  "printedText": "[On Play] You may trash 1 Event card from your hand: Draw 2 cards.\n[End of Your Turn] If you have 7 or more DON!! cards, set up to two of them as active.",
  "keywords": [],
  "abilities": [
    {
      "timing": "onPlay",
      "cost": {
        "type": "trashFromHand",
        "minCards": 1,
        "maxCards": 1,
        "filters": ["event"],
        "may": true
      },
      "actions": [
        {
          "type": "draw",
          "count": 2,
          "side": "self"
        }
      ]
    },
    {
      "timing": "endOfYourTurn",
      "condition": {
        "field": "selfDonCount",
        "op": ">=",
        "value": 7
      },
      "selectors": {
        "selfDonInCostArea": {
          "side": "self",
          "type": "don",
          "zones": ["costArea"],
          "min": 0,
          "max": 2,
          "upTo": true,
          "whoChooses": "self",
          "bindAs": "selfDonInCostArea"
        }
      },
      "actions": [
        {
          "type": "setState",
          "state": "active",
          "target": "selfDonInCostArea"
        }
      ]
    }
  ]
}
