{
  "id": "OP03-040",
  "set": "OP03",
  "number": 40,
  "name": "Nami",
  "category": "Leader",
  "colors": [
    "Blue"
  ],
  "attribute": "Wisdom",
  "types": [
    "East Blue"
  ],
  "rarity": "C",
  "art": "/cards/OP03/OP03-040.png",
  "stats": {
    "cost": null,
    "power": null,
    "life": 5000,
    "counter": {
      "present": false,
      "value": 0
    }
  },
  "keywords": [
    "On Play"
  ],
  "trigger": null,
  "text": "As an additional rule, when your deck reaches 0 cards, you win the match instead of losing it. [DON!!x1] When your opponent takes damage to their Life through the attack of this Leader, you may trash 1 card from the top of your deck.",
  "abilities": [
    {
      "timing": "On Play",
      "frequency": null,
      "donReq": 1,
      "cost": {
        "restDonFromCostArea": 1
      },
      "effect": {
        "text": "When your opponent takes damage to their Life through the attack of this Leader, you may trash 1 card from the top of your deck.",
        "powerMod": null,
        "targets": [
          "opponent:Character"
        ],
        "conditions": [
          "attacking:Leader"
        ],
        "giveDon": null
      }
    }
  ],
  "meta": {
    "notes": "The card is a sample image, indicated by the 'SAMPLE' watermark. The rarity is inferred from the 'C' in the bottom right corner. The text is fully readable."
  }
}
