{
  "id": "ST25-004",
  "set": "ST25",
  "number": 4,
  "name": "Buggy",
  "category": "Character",
  "colors": ["Blue"],
  "attribute": null,
  "types": ["The Four Emperors", "Cross Guild"],
  "rarity": "SR",
  "art": "/cards/ST25/ST25-004.png",
  "stats": {
    "cost": 4,
    "power": 1000,
    "life": null,
    "counter": { "present": true, "value": 1000 }
  },
  "keywords": [],
  "trigger": null,
  "text": "[Activate:Main] You may trash 1 card from your hand and trash this Character: If your Leader is [Buggy], play up to 1 {Cross Guild} type Character card with a cost of 6 or less from your hand.",
  "abilities": [
    {
      "timing": "Activate: Main",
      "frequency": null,
      "donReq": null,
      "cost": { "restDonFromCostArea": 0 },
      "effect": {
        "text": "You may trash 1 card from your hand and trash this Character: If your Leader is [Buggy], play up to 1 {Cross Guild} type Character card with a cost of 6 or less from your hand.",
        "grants": [],
        "powerMod": null,
        "targets": ["self"],
        "conditions": ["mayTrash1FromHand", "trashThisCharacter", "leaderIsBuggy"]
      }
    }
  ],
  "meta": { "notes": null }
}
