{
  "cardName": "Cross Guild",
  "cardId": "OP09-057",
  "cardType": "event",
  "colors": ["blue"],
  "cost": 1,
  "types": ["Cross Guild"],
  "traits": ["crossGuild"],
  "rarity": "R",
  "setId": "OP09",
  "cardNumber": "057",
  "printedText": "[Main] Look at the top 4 cards of your deck, reveal and add to your hand up to 1 card with the {Cross Guild} type. Then, return the rest to the bottom of the deck in any order.\n[Trigger] Activate this card's Main effect.",
  "keywords": [],
  "abilities": [
    {
      "timing": "main",
      "selectors": {
        "crossGuildFromDeck": {
          "side": "self",
          "type": "any",
          "zones": ["deck"],
          "filters": [
            {
              "field": "traits",
              "op": "=",
              "value": "crossGuild"
            }
          ],
          "min": 0,
          "max": 1,
          "upTo": true,
          "whoChooses": "self"
        }
      },
      "actions": [
        {
          "type": "search",
          "sourceZone": "deck",
          "selector": "crossGuildFromDeck",
          "reveal": true,
          "addTo": "hand",
          "ordering": "any",
          "topCount": 4,
          "moveRemainingTo": "bottomOfDeck",
          "remainingOrdering": "chosen"
        }
      ]
    },
    {
      "timing": "trigger",
      "actions": [
        {
          "type": "activateSelfAbility",
          "abilityTiming": "main"
        }
      ]
    }
  ]
}
