{
  "cardName": "Bellamy",
  "cardId": "P-039",
  "cardType": "character",
  "colors": ["yellow"],
  "cost": 5,
  "power": 6000,
  "counter": 0,
  "attributes": ["strike"],
  "types": ["Bellamy Pirates"],
  "traits": ["bellamyPirates"],
  "rarity": "P",
  "setId": "P",
  "cardNumber": "P-039",
  "printedText": "Banish (When this card deals damage, the target card is trashed without activating its Trigger.)\n[DON!! x2] When you have 0 Life this Character gains +2000 power.",
  "keywords": ["Banish"],
  "abilities": [
    {
      "timing": "static",
      "condition": {
        "logic": "AND",
        "all": [
          {
            "field": "isGivenDon",
            "op": ">=",
            "value": 2
          },
          {
            "field": "life",
            "op": "=",
            "value": 0
          }
        ]
      },
      "selectors": {
        "thisCharacter": {
          "side": "self",
          "type": "thisCard"
        }
      },
      "actions": [
        {
          "type": "modifyStat",
          "stat": "power",
          "mode": "add",
          "amount": 2000,
          "duration": "thisTurn",
          "target": "thisCharacter"
        }
      ]
    }
  ]
}
