{
  "power": 0,
  "cardType": "character",
  "cardId": "EB03-016",
  "printedText": "[On Play] If your Leader is [Kouzuki Oden], draw 1 card.\n[Activate:Main] You may trash this Character: Give up to 1 rested DON!! card to your {Land of Wano} type Leader.",
  "types": [
    "Land of Wano",
    "Kouzuki Clan"
  ],
  "cardNumber": "016",
  "keywords": [
    "On Play",
    "Activate:Main"
  ],
  "abilities": [
    {
      "condition": {
        "value": "Kouzuki Oden",
        "field": "leaderName",
        "op": "="
      },
      "selectors": {},
      "timing": "onPlay",
      "actions": [
        {
          "count": 1,
          "type": "draw"
        }
      ]
    },
    {
      "cost": {
        "type": "trashThis"
      },
      "selectors": {},
      "timing": "activateMain",
      "actions": [
        {
          "type": "attachDon",
          "target": {
            "filters": [
              {
                "value": "Land of Wano",
                "field": "types",
                "op": "="
              }
            ],
            "zones": [
              "leader"
            ],
            "min": 1,
            "max": 1,
            "type": "leader",
            "side": "self",
            "whoChooses": "self"
          },
          "selector": {
            "filters": [
              {
                "value": true,
                "field": "rested",
                "op": "="
              }
            ],
            "zones": [
              "costArea"
            ],
            "upTo": true,
            "min": 0,
            "max": 1,
            "type": "don",
            "side": "self",
            "whoChooses": "self"
          }
        }
      ]
    }
  ],
  "setId": "EB03",
  "counter": 0,
  "cardName": "Kouzuki Hiyori",
  "rarity": "C",
  "cost": 1,
  "colors": [
    "green"
  ],
  "attributes": [
    "wisdom"
  ],
  "traits": [
    "landOfWano",
    "kouzukiClan"
  ]
}
