{
  "power": 5000,
  "cardType": "character",
  "cardId": "EB03-037",
  "printedText": "[On Play] If you have 7 or more DON!! cards on your field, your Leader and all of your Characters with the {ODYSSEY} type gain +1000 power until the end of your opponent's next turn.",
  "types": [
    "ODYSSEY"
  ],
  "abilities": [
    {
      "condition": {
        "op": ">=",
        "field": "selfDonOnField",
        "value": 7
      },
      "selectors": {},
      "timing": "onPlay",
      "actions": [
        {
          "type": "modifyStat",
          "mode": "add",
          "stat": "power",
          "duration": "untilEndOfOpponentsNextTurn",
          "amount": 1000,
          "target": {
            "zones": [
              "leader"
            ],
            "type": "leader",
            "max": 1,
            "min": 1,
            "side": "self",
            "whoChooses": "system"
          }
        },
        {
          "type": "modifyStat",
          "mode": "add",
          "stat": "power",
          "duration": "untilEndOfOpponentsNextTurn",
          "amount": 1000,
          "target": {
            "filters": [
              {
                "op": "=",
                "field": "types",
                "value": "ODYSSEY"
              }
            ],
            "zones": [
              "character"
            ],
            "upTo": true,
            "type": "character",
            "max": 999,
            "min": 0,
            "side": "self",
            "whoChooses": "system"
          }
        }
      ],
      "frequency": "none"
    }
  ],
  "setId": "EB03",
  "counter": 2000,
  "cardNumber": "037",
  "cardName": "Lim",
  "rarity": "R",
  "cost": 4,
  "colors": [
    "purple"
  ],
  "attributes": [
    "wisdom"
  ],
  "traits": [
    "odyssey"
  ]
}
