{
  "power": 0,
  "cardType": "event",
  "cardId": "EB02-041",
  "printedText": "On Play If your leader has the type {Straw Hat Crew}, draw 1 card.\n\nActivate: Main You may rest this stage: If the number of DON!! cards in your field is equal or less to the number of DON!! cards on your opponent's field, give up to 1 of your {Straw Hat Crew} type characters +2000 power until the end of your next turn.",
  "types": [
    "Straw Hat Crew"
  ],
  "cardNumber": "041",
  "abilities": [
    {
      "condition": {
        "value": "Straw Hat Crew",
        "field": "leaderType",
        "op": "="
      },
      "selectors": {},
      "timing": "onPlay",
      "actions": [
        {
          "count": 1,
          "type": "draw"
        }
      ],
      "frequency": "none"
    },
    {
      "cost": {
        "type": "restThis"
      },
      "selectors": {},
      "timing": "activateMain",
      "actions": [
        {
          "type": "modifyStat",
          "amount": 2000,
          "mode": "add",
          "stat": "power",
          "duration": "untilStartOfYourNextTurn",
          "condition": {
            "value": true,
            "field": "donSelfLessOrEqualOpponent",
            "op": "="
          },
          "target": {
            "filters": [
              {
                "value": "Straw Hat Crew",
                "field": "types",
                "op": "="
              }
            ],
            "side": "self",
            "upTo": true,
            "min": 0,
            "max": 1,
            "type": "character",
            "whoChooses": "self"
          }
        }
      ],
      "frequency": "none"
    }
  ],
  "setId": "EB02",
  "counter": 0,
  "cardName": "Going Merry",
  "rarity": "R",
  "cost": 1,
  "colors": [
    "blue"
  ],
  "traits": [
    "strawHatCrew"
  ]
}
